kraken_sdk/__init__.py
kraken_sdk/_version.py
kraken_sdk/client.py
kraken_sdk/config.py
kraken_sdk/exceptions.py
kraken_sdk/transport.py
kraken_sdk/types.py
kraken_sdk/_generated/__init__.py
kraken_sdk/_generated/models.py
kraken_sdk/_utils/__init__.py
kraken_sdk/_utils/files.py
kraken_sdk/_utils/polling.py
kraken_sdk/resources/__init__.py
kraken_sdk/resources/_base.py
kraken_sdk/resources/auth.py
kraken_sdk/resources/benchmarks.py
kraken_sdk/resources/info.py
kraken_sdk/resources/jobs.py
kraken_sdk/resources/provider_api_keys.py
kraken_sdk/resources/sources.py
kraken_captia-0.1.2.dist-info/METADATA
kraken_captia-0.1.2.dist-info/WHEEL
kraken_captia-0.1.2.dist-info/RECORD
