Metadata-Version: 2.4
Name: kraken-captia
Version: 0.1.2
Summary: Official Python SDK for Kraken document processing API
Project-URL: Homepage, https://github.com/Capt-IA/Kraken-SDK
Project-URL: Documentation, https://github.com/Capt-IA/Kraken-SDK/tree/main/kraken-sdk-python
Project-URL: Repository, https://github.com/Capt-IA/Kraken-SDK
Project-URL: Issues, https://github.com/Capt-IA/Kraken-SDK/issues
Author-email: Capt IA <contact@capt-ia.com>
License-Expression: MIT
Keywords: ai,annotation,api,document-processing,extraction,kraken,ocr,sdk
Classifier: Development Status :: 4 - Beta
Classifier: Intended Audience :: Developers
Classifier: License :: OSI Approved :: MIT License
Classifier: Operating System :: OS Independent
Classifier: Programming Language :: Python :: 3
Classifier: Programming Language :: Python :: 3.11
Classifier: Programming Language :: Python :: 3.12
Classifier: Topic :: Software Development :: Libraries :: Python Modules
Classifier: Typing :: Typed
Requires-Python: >=3.11
Requires-Dist: httpx>=0.25.0
Requires-Dist: pydantic>=2.0.0
Requires-Dist: typing-extensions>=4.0.0
Provides-Extra: dev
Requires-Dist: datamodel-code-generator[http]>=0.25.0; extra == 'dev'
Requires-Dist: mypy>=1.0.0; extra == 'dev'
Requires-Dist: pytest-asyncio>=0.21.0; extra == 'dev'
Requires-Dist: pytest>=7.0.0; extra == 'dev'
Requires-Dist: respx>=0.20.0; extra == 'dev'
Requires-Dist: ruff>=0.1.0; extra == 'dev'
Requires-Dist: types-requests; extra == 'dev'
